swmm_api/__init__.py
swmm_api/_io_helpers/__init__.py
swmm_api/_io_helpers/_config.py
swmm_api/_io_helpers/_encoding.py
swmm_api/_io_helpers/_read_bin.py
swmm_api/_io_helpers/_read_txt.py
swmm_api/analyse_model/__init__.py
swmm_api/analyse_model/input_summary.py
swmm_api/analyse_simulation/__init__.py
swmm_api/analyse_simulation/gis_export.py
swmm_api/analyse_simulation/instability_index.py
swmm_api/external_files/__init__.py
swmm_api/external_files/climate_file.py
swmm_api/external_files/dat_timeseries.py
swmm_api/external_files/following_values.py
swmm_api/hotstart_file/__init__.py
swmm_api/hotstart_file/hst.py
swmm_api/input_file/__init__.py
swmm_api/input_file/_type_converter.py
swmm_api/input_file/helpers.py
swmm_api/input_file/helpers_dummy.py
swmm_api/input_file/inp.py
swmm_api/input_file/section_labels.py
swmm_api/input_file/section_lists.py
swmm_api/input_file/section_types.py
swmm_api/input_file/macros/__init__.py
swmm_api/input_file/macros/_combined_objects.py
swmm_api/input_file/macros/_helpers.py
swmm_api/input_file/macros/_plotting_helpers.py
swmm_api/input_file/macros/_snippets.py
swmm_api/input_file/macros/check.py
swmm_api/input_file/macros/collection.py
swmm_api/input_file/macros/combine_dwf.py
swmm_api/input_file/macros/compare.py
swmm_api/input_file/macros/convert_model.py
swmm_api/input_file/macros/convert_object.py
swmm_api/input_file/macros/cross_section_curve.py
swmm_api/input_file/macros/curve.py
swmm_api/input_file/macros/cut_model.py
swmm_api/input_file/macros/edit.py
swmm_api/input_file/macros/filter.py
swmm_api/input_file/macros/geo.py
swmm_api/input_file/macros/gis.py
swmm_api/input_file/macros/graph.py
swmm_api/input_file/macros/macros.py
swmm_api/input_file/macros/plotting_longitudinal.py
swmm_api/input_file/macros/plotting_map.py
swmm_api/input_file/macros/plotting_map_bokeh.py
swmm_api/input_file/macros/plotting_map_leaflet.py
swmm_api/input_file/macros/plotting_map_plotly.py
swmm_api/input_file/macros/plotting_sub_map.py
swmm_api-0.4.71.dist-info/LICENSE
swmm_api-0.4.71.dist-info/METADATA
swmm_api-0.4.71.dist-info/WHEEL
swmm_api-0.4.71.dist-info/top_level.txt
swmm_api-0.4.71.dist-info/RECORD
