Metadata-Version: 2.2
Name: swmm-api
Version: 0.4.71
Summary: API for reading, manipulating and running US-EPA-SWMM-Projects
Author-email: Markus Pichler <markus.pichler@tugraz.at>
License: MIT
Project-URL: Documentation, https://markuspichler.gitlab.io/swmm_api
Project-URL: Changelog, https://gitlab.com/markuspichler/swmm_api/-/blob/main/CHANGELOG.md
Project-URL: homepage, https://gitlab.com/markuspichler/swmm_api
Project-URL: funding, https://www.buymeacoffee.com/MarkusP
Project-URL: Issues, https://gitlab.com/markuspichler/swmm_api/-/issues
Keywords: swmm,environment,civil_engineering,api
Classifier: Programming Language :: Python :: 3
Classifier: License :: OSI Approved :: MIT License
Classifier: Operating System :: OS Independent
Classifier: Development Status :: 4 - Beta
Classifier: Natural Language :: English
Classifier: Topic :: Scientific/Engineering
Classifier: Topic :: Scientific/Engineering :: Hydrology
Classifier: Intended Audience :: Science/Research
Requires-Python: >=3.8
License-File: LICENSE
Requires-Dist: pandas
Requires-Dist: tqdm
Requires-Dist: packaging
Provides-Extra: macros
Requires-Dist: networkx; extra == "macros"
Requires-Dist: pyarrow; extra == "macros"
Requires-Dist: matplotlib; extra == "macros"
Requires-Dist: SWMM_xsections_shape_generator; extra == "macros"
Requires-Dist: pyswmm; extra == "macros"
Provides-Extra: gis
Requires-Dist: Shapely; extra == "gis"
Requires-Dist: pyproj; extra == "gis"
Requires-Dist: Rtree; extra == "gis"
Requires-Dist: geopandas; extra == "gis"
Provides-Extra: full
Requires-Dist: swmm-api[gis,macros]; extra == "full"
Provides-Extra: docs
Requires-Dist: swmm-api[full]; extra == "docs"
Requires-Dist: sphinx; extra == "docs"
Requires-Dist: nbsphinx; extra == "docs"
Requires-Dist: recommonmark; extra == "docs"
Requires-Dist: myst-parser; extra == "docs"
Requires-Dist: pydata_sphinx_theme; extra == "docs"
Requires-Dist: sphinx-codeautolink; extra == "docs"
Requires-Dist: sphinx-favicon; extra == "docs"
Provides-Extra: testing
Requires-Dist: swmm-api[full]; extra == "testing"
Requires-Dist: pytest; extra == "testing"
